cellink/__init__.py
cellink/graph.py
cellink/node.py
cellink/registry.py
cellink-1.3.10.dist-info/LICENSE
cellink-1.3.10.dist-info/METADATA
cellink-1.3.10.dist-info/WHEEL
cellink-1.3.10.dist-info/top_level.txt
cellink-1.3.10.dist-info/RECORD
