Metadata-Version: 2.1
Name: cellink
Version: 1.3.10
Summary: An easy-to-use engine that allows python programmers to code with Chain of Responsibility Pattern
Author: Zhai Menghua
Author-email: viibridges@gmail.com
License: Apache 2.0
Keywords: chain of responsibility,design pattern
Classifier: Development Status :: 4 - Beta
Classifier: Intended Audience :: Developers
Classifier: License :: OSI Approved :: Apache Software License
Classifier: Programming Language :: Python :: 3
Classifier: Programming Language :: Python :: 3.6
Classifier: Programming Language :: Python :: 3.7
Classifier: Programming Language :: Python :: 3.8
Classifier: Programming Language :: Python :: 3.9
Classifier: Topic :: Software Development :: Libraries
Requires-Python: >=3.6
License-File: LICENSE
Requires-Dist: graphviz (>=0.16.0)
